transbase-0.0.6.data/purelib/lib/libtci.dylib
transbase-0.0.6.data/purelib/transbase/__init__.py
transbase-0.0.6.data/purelib/transbase/error.py
transbase-0.0.6.data/purelib/transbase/install.py
transbase-0.0.6.data/purelib/transbase/tci.py
transbase-0.0.6.data/purelib/transbase/transbase.py
transbase-0.0.6.data/scripts/install_tci
transbase-0.0.6.dist-info/LICENSE
transbase-0.0.6.dist-info/METADATA
transbase-0.0.6.dist-info/WHEEL
transbase-0.0.6.dist-info/top_level.txt
transbase-0.0.6.dist-info/RECORD
