Metadata-Version: 2.1
Name: transbase
Version: 0.0.6
Summary: Python Transbase Client
Home-page: https://www.transaction.de
Author: Daniel Loibl
Author-email: loibl@transaction.de
License: MIT
Platform: UNKNOWN
Requires-Python: >=3.9
License-File: LICENSE
Requires-Dist: requests
